pubkey2address/__init__.py
pubkey2address/gpk_to_btc_address.py
pubkey2address/gpk_to_dot_address.py
pubkey2address/gpk_to_xrp_address.py
pubkey2address-1.0.0.dist-info/METADATA
pubkey2address-1.0.0.dist-info/WHEEL
pubkey2address-1.0.0.dist-info/top_level.txt
pubkey2address-1.0.0.dist-info/RECORD
