Metadata-Version: 2.1
Name: pubkey2address
Version: 1.0.0
Summary: simple tool
Home-page: https://github.com/Nevquit/iWAN_Request
Author: vSir
Author-email: weiguo341@gmail.com
Classifier: Programming Language :: Python :: 3
Classifier: License :: OSI Approved :: MIT License
Classifier: Operating System :: OS Independent
Requires-Dist: xrpl-py (==1.6.0)
Requires-Dist: coincurve (==13.0.0)
Requires-Dist: bit (==0.7.2)
Requires-Dist: substrate-interface (==1.1)
